{"directed": false, "graph": [], "nodes": [{"name": "rh_paracentral", "weight": 0.3150110674526147, "pos": [0, 55], "ts_group_id": 0, "label": "paracentral", "input_id": 11, "layer_pos": 0, "y": 55, "x": 0, "brain_side": "right", "id": 11, "func_id": "2"}, {"name": "lh_paracentral", "weight": 0.45566631504911176, "pos": [0, 225], "ts_group_id": 0, "label": "paracentral", "input_id": 45, "layer_pos": 0, "y": 225, "x": 0, "brain_side": "left", "id": 45, "func_id": "2"}, {"name": "rh_paracentral", "weight": 0.41376725898803596, "pos": [3, 55], "ts_group_id": 0, "label": "paracentral", "input_id": 11, "layer_pos": 1, "y": 55, "x": 3, "brain_side": "right", "id": 79, "func_id": "2"}, {"name": "lh_paracentral", "weight": 0.57579160823539388, "pos": [3, 225], "ts_group_id": 0, "label": "paracentral", "input_id": 45, "layer_pos": 1, "y": 225, "x": 3, "brain_side": "left", "id": 113, "func_id": "2"}, {"name": "rh_paracentral", "weight": 0.22234722689295786, "pos": [6, 55], "ts_group_id": 0, "label": "paracentral", "input_id": 11, "layer_pos": 2, "y": 55, "x": 6, "brain_side": "right", "id": 147, "func_id": "2"}, {"name": "lh_paracentral", "weight": 0.33585572983020057, "pos": [6, 225], "ts_group_id": 0, "label": "paracentral", "input_id": 45, "layer_pos": 2, "y": 225, "x": 6, "brain_side": "left", "id": 181, "func_id": "2"}], "links": [{"source": 0, "target": 3}, {"source": 0, "target": 2}, {"source": 1, "target": 3}, {"source": 1, "target": 2}, {"source": 2, "target": 4}, {"source": 2, "target": 5}, {"source": 3, "target": 4}, {"source": 3, "target": 5}], "multigraph": false}