{"directed": false, "graph": [], "nodes": [{"name": "lh_pericalcarine", "weight": 0.12085478216143733, "pos": [6, 280], "ts_group_id": 0, "label": "pericalcarine", "input_id": 56, "layer_pos": 2, "y": 280, "x": 6, "brain_side": "left", "id": 192, "func_id": "1"}, {"name": "rh_pericalcarine", "weight": 0.076247536782798248, "pos": [9, 110], "ts_group_id": 0, "label": "pericalcarine", "input_id": 22, "layer_pos": 3, "y": 110, "x": 9, "brain_side": "right", "id": 226, "func_id": "1"}, {"name": "lh_precuneus", "weight": 0.076555584938296159, "pos": [6, 270], "ts_group_id": 0, "label": "precuneus", "input_id": 54, "layer_pos": 2, "y": 270, "x": 6, "brain_side": "left", "id": 190, "func_id": "7"}, {"name": "rh_pericalcarine", "weight": 0.49414536592478753, "pos": [0, 110], "ts_group_id": 0, "label": "pericalcarine", "input_id": 22, "layer_pos": 0, "y": 110, "x": 0, "brain_side": "right", "id": 22, "func_id": "1"}, {"name": "lh_cuneus", "weight": 0.072994725784895215, "pos": [0, 275], "ts_group_id": 0, "label": "cuneus", "input_id": 55, "layer_pos": 0, "y": 275, "x": 0, "brain_side": "left", "id": 55, "func_id": "1"}, {"name": "lh_pericalcarine", "weight": 0.52398044770448493, "pos": [0, 280], "ts_group_id": 0, "label": "pericalcarine", "input_id": 56, "layer_pos": 0, "y": 280, "x": 0, "brain_side": "left", "id": 56, "func_id": "1"}, {"name": "rh_pericalcarine", "weight": 0.4285813888940766, "pos": [3, 110], "ts_group_id": 0, "label": "pericalcarine", "input_id": 22, "layer_pos": 1, "y": 110, "x": 3, "brain_side": "right", "id": 90, "func_id": "1"}, {"name": "lh_pericalcarine", "weight": 0.41475140070022376, "pos": [3, 280], "ts_group_id": 0, "label": "pericalcarine", "input_id": 56, "layer_pos": 1, "y": 280, "x": 3, "brain_side": "left", "id": 124, "func_id": "1"}, {"name": "rh_pericalcarine", "weight": 0.18639726989672684, "pos": [6, 110], "ts_group_id": 0, "label": "pericalcarine", "input_id": 22, "layer_pos": 2, "y": 110, "x": 6, "brain_side": "right", "id": 158, "func_id": "1"}], "links": [{"source": 0, "target": 6}, {"source": 0, "target": 7}, {"source": 0, "target": 1}, {"source": 1, "target": 2}, {"source": 1, "target": 8}, {"source": 2, "target": 6}, {"source": 2, "target": 7}, {"source": 3, "target": 6}, {"source": 3, "target": 7}, {"source": 4, "target": 6}, {"source": 4, "target": 7}, {"source": 5, "target": 6}, {"source": 5, "target": 7}, {"source": 6, "target": 8}, {"source": 7, "target": 8}], "multigraph": false}