{"directed": false, "graph": [], "nodes": [{"name": "lh_inferiorparietal", "weight": 1.0, "pos": [3, 265], "ts_group_id": 0, "label": "inferiorparietal", "input_id": 53, "layer_pos": 1, "y": 265, "x": 3, "brain_side": "left", "id": 121, "func_id": "7"}, {"name": "lh_inferiorparietal", "weight": 0.7, "pos": [0, 265], "ts_group_id": 0, "label": "inferiorparietal", "input_id": 53, "layer_pos": 0, "y": 265, "x": 0, "brain_side": "left", "id": 53, "func_id": "7"}, {"name": "lh_inferiorparietal", "weight": 0.9, "pos": [6, 265], "ts_group_id": 0, "label": "inferiorparietal", "input_id": 53, "layer_pos": 2, "y": 265, "x": 6, "brain_side": "left", "id": 189, "func_id": "7"}], "links": [{"source": 0, "target": 1}, {"source": 0, "target": 2}], "multigraph": false}