{"directed": false, "graph": [], "nodes": [{"name": "rh_superiortemporal", "weight": 0.8, "pos": [3, 160], "ts_group_id": 0, "label": "superiortemporal", "input_id": 32, "layer_pos": 1, "y": 160, "x": 3, "brain_side": "right", "id": 100, "func_id": "2"}, {"name": "rh_insula", "weight": 0.8, "pos": [3, 170], "ts_group_id": 0, "label": "insula", "input_id": 34, "layer_pos": 1, "y": 170, "x": 3, "brain_side": "right", "id": 102, "func_id": "4"}, {"name": "rh_superiortemporal", "weight": 1.0, "pos": [6, 160], "ts_group_id": 0, "label": "superiortemporal", "input_id": 32, "layer_pos": 2, "y": 160, "x": 6, "brain_side": "right", "id": 168, "func_id": "2"}, {"name": "rh_insula", "weight": 0.8, "pos": [6, 170], "ts_group_id": 0, "label": "insula", "input_id": 34, "layer_pos": 2, "y": 170, "x": 6, "brain_side": "right", "id": 170, "func_id": "4"}, {"name": "rh_paracentral", "weight": 1.0, "pos": [6, 55], "ts_group_id": 0, "label": "paracentral", "input_id": 11, "layer_pos": 2, "y": 55, "x": 6, "brain_side": "right", "id": 147, "func_id": "2"}, {"name": "rh_precuneus", "weight": 0.8, "pos": [3, 100], "ts_group_id": 0, "label": "precuneus", "input_id": 20, "layer_pos": 1, "y": 100, "x": 3, "brain_side": "right", "id": 88, "func_id": "7"}], "links": [{"source": 0, "target": 2}, {"source": 0, "target": 3}, {"source": 1, "target": 2}, {"source": 1, "target": 3}, {"source": 2, "target": 5}, {"source": 4, "target": 5}], "multigraph": false}