{"directed": false, "graph": [], "nodes": [{"name": "rh_lingual", "weight": 0.5172413793103449, "pos": [6, 120], "ts_group_id": 0, "label": "lingual", "input_id": 24, "layer_pos": 2, "y": 120, "x": 6, "brain_side": "right", "id": 160, "func_id": "1"}, {"name": "lh_lingual", "weight": 0.4482758620689655, "pos": [6, 290], "ts_group_id": 0, "label": "lingual", "input_id": 58, "layer_pos": 2, "y": 290, "x": 6, "brain_side": "left", "id": 194, "func_id": "1"}, {"name": "rh_lingual", "weight": 0.47619047619047616, "pos": [9, 120], "ts_group_id": 0, "label": "lingual", "input_id": 24, "layer_pos": 3, "y": 120, "x": 9, "brain_side": "right", "id": 228, "func_id": "1"}, {"name": "rh_pericalcarine", "weight": 0.5238095238095238, "pos": [9, 110], "ts_group_id": 0, "label": "pericalcarine", "input_id": 22, "layer_pos": 3, "y": 110, "x": 9, "brain_side": "right", "id": 226, "func_id": "1"}, {"name": "rh_pericalcarine", "weight": 0.5517241379310345, "pos": [6, 110], "ts_group_id": 0, "label": "pericalcarine", "input_id": 22, "layer_pos": 2, "y": 110, "x": 6, "brain_side": "right", "id": 158, "func_id": "1"}, {"name": "rh_pericalcarine", "weight": 0.59375, "pos": [0, 110], "ts_group_id": 0, "label": "pericalcarine", "input_id": 22, "layer_pos": 0, "y": 110, "x": 0, "brain_side": "right", "id": 22, "func_id": "1"}, {"name": "rh_lingual", "weight": 0.6875, "pos": [0, 120], "ts_group_id": 0, "label": "lingual", "input_id": 24, "layer_pos": 0, "y": 120, "x": 0, "brain_side": "right", "id": 24, "func_id": "1"}, {"name": "rh_pericalcarine", "weight": 0.7741935483870968, "pos": [3, 110], "ts_group_id": 0, "label": "pericalcarine", "input_id": 22, "layer_pos": 1, "y": 110, "x": 3, "brain_side": "right", "id": 90, "func_id": "1"}, {"name": "rh_lingual", "weight": 0.8064516129032258, "pos": [3, 120], "ts_group_id": 0, "label": "lingual", "input_id": 24, "layer_pos": 1, "y": 120, "x": 3, "brain_side": "right", "id": 92, "func_id": "1"}, {"name": "lh_lingual", "weight": 0.46875, "pos": [0, 290], "ts_group_id": 0, "label": "lingual", "input_id": 58, "layer_pos": 0, "y": 290, "x": 0, "brain_side": "left", "id": 58, "func_id": "1"}, {"name": "lh_lingual", "weight": 0.5806451612903226, "pos": [3, 290], "ts_group_id": 0, "label": "lingual", "input_id": 58, "layer_pos": 1, "y": 290, "x": 3, "brain_side": "left", "id": 126, "func_id": "1"}], "links": [{"source": 0, "target": 2}, {"source": 0, "target": 7}, {"source": 0, "target": 8}, {"source": 0, "target": 3}, {"source": 0, "target": 10}, {"source": 1, "target": 2}, {"source": 1, "target": 7}, {"source": 1, "target": 8}, {"source": 1, "target": 3}, {"source": 1, "target": 10}, {"source": 2, "target": 4}, {"source": 3, "target": 4}, {"source": 4, "target": 7}, {"source": 4, "target": 8}, {"source": 4, "target": 10}, {"source": 5, "target": 7}, {"source": 5, "target": 8}, {"source": 5, "target": 10}, {"source": 6, "target": 7}, {"source": 6, "target": 8}, {"source": 6, "target": 10}, {"source": 7, "target": 9}, {"source": 8, "target": 9}, {"source": 9, "target": 10}], "multigraph": false}