{"directed": false, "graph": [], "nodes": [{"slice_pos": 0, "name": "lh_parsopercularis", "weight": 0.17857142857142858, "pos": [0, 200], "ts_group_id": 0, "label": "parsopercularis", "input_id": 40, "func_id": "4", "y": 200, "x": 0, "brain_side": "left", "id": 40}, {"slice_pos": 4, "name": "lh_precentral", "weight": 0.17857142857142858, "pos": [12, 220], "ts_group_id": 0, "label": "precentral", "input_id": 44, "func_id": "2", "y": 220, "x": 12, "brain_side": "left", "id": 316}, {"slice_pos": 0, "name": "lh_precentral", "weight": 0.4642857142857143, "pos": [0, 220], "ts_group_id": 0, "label": "precentral", "input_id": 44, "func_id": "2", "y": 220, "x": 0, "brain_side": "left", "id": 44}, {"slice_pos": 2, "name": "rh_precentral", "weight": 0.21428571428571427, "pos": [6, 50], "ts_group_id": 0, "label": "precentral", "input_id": 10, "func_id": "2", "y": 50, "x": 6, "brain_side": "right", "id": 146}, {"slice_pos": 1, "name": "lh_precentral", "weight": 0.75, "pos": [3, 220], "ts_group_id": 0, "label": "precentral", "input_id": 44, "func_id": "2", "y": 220, "x": 3, "brain_side": "left", "id": 112}, {"slice_pos": 3, "name": "lh_precentral", "weight": 0.25, "pos": [9, 220], "ts_group_id": 0, "label": "precentral", "input_id": 44, "func_id": "2", "y": 220, "x": 9, "brain_side": "left", "id": 248}, {"slice_pos": 0, "name": "lh_postcentral", "weight": 0.5714285714285714, "pos": [0, 250], "ts_group_id": 0, "label": "postcentral", "input_id": 50, "func_id": "2", "y": 250, "x": 0, "brain_side": "left", "id": 50}, {"slice_pos": 1, "name": "rh_postcentral", "weight": 0.17857142857142858, "pos": [3, 80], "ts_group_id": 0, "label": "postcentral", "input_id": 16, "func_id": "2", "y": 80, "x": 3, "brain_side": "right", "id": 84}, {"slice_pos": 1, "name": "lh_postcentral", "weight": 0.6785714285714286, "pos": [3, 250], "ts_group_id": 0, "label": "postcentral", "input_id": 50, "func_id": "2", "y": 250, "x": 3, "brain_side": "left", "id": 118}, {"slice_pos": 1, "name": "lh_supramarginal", "weight": 0.17857142857142858, "pos": [3, 255], "ts_group_id": 0, "label": "supramarginal", "input_id": 51, "func_id": "4", "y": 255, "x": 3, "brain_side": "left", "id": 119}, {"slice_pos": 2, "name": "rh_postcentral", "weight": 0.2857142857142857, "pos": [6, 80], "ts_group_id": 0, "label": "postcentral", "input_id": 16, "func_id": "2", "y": 80, "x": 6, "brain_side": "right", "id": 152}, {"slice_pos": 2, "name": "lh_precentral", "weight": 0.42857142857142855, "pos": [6, 220], "ts_group_id": 0, "label": "precentral", "input_id": 44, "func_id": "2", "y": 220, "x": 6, "brain_side": "left", "id": 180}, {"slice_pos": 2, "name": "lh_postcentral", "weight": 0.7142857142857143, "pos": [6, 250], "ts_group_id": 0, "label": "postcentral", "input_id": 50, "func_id": "2", "y": 250, "x": 6, "brain_side": "left", "id": 186}, {"slice_pos": 2, "name": "lh_supramarginal", "weight": 0.17857142857142858, "pos": [6, 255], "ts_group_id": 0, "label": "supramarginal", "input_id": 51, "func_id": "4", "y": 255, "x": 6, "brain_side": "left", "id": 187}, {"slice_pos": 3, "name": "rh_postcentral", "weight": 0.21428571428571427, "pos": [9, 80], "ts_group_id": 0, "label": "postcentral", "input_id": 16, "func_id": "2", "y": 80, "x": 9, "brain_side": "right", "id": 220}, {"slice_pos": 3, "name": "lh_postcentral", "weight": 0.2857142857142857, "pos": [9, 250], "ts_group_id": 0, "label": "postcentral", "input_id": 50, "func_id": "2", "y": 250, "x": 9, "brain_side": "left", "id": 254}], "links": [{"source": 0, "target": 4, "weight": 0.5}, {"source": 1, "target": 5, "weight": 0.4444444444444444}, {"source": 1, "target": 15, "weight": 0.3}, {"source": 2, "target": 4, "weight": 0.3170731707317073}, {"source": 2, "target": 8, "weight": 0.24390243902439024}, {"source": 2, "target": 9, "weight": 0.04878048780487805}, {"source": 3, "target": 4, "weight": 0.08333333333333333}, {"source": 3, "target": 14, "weight": 0.3}, {"source": 3, "target": 7, "weight": 0.2222222222222222}, {"source": 3, "target": 5, "weight": 0.3}, {"source": 4, "target": 6, "weight": 0.3111111111111111}, {"source": 4, "target": 11, "weight": 0.16666666666666666}, {"source": 4, "target": 12, "weight": 0.2833333333333333}, {"source": 4, "target": 13, "weight": 0.08333333333333333}, {"source": 5, "target": 13, "weight": 0.125}, {"source": 5, "target": 11, "weight": 0.1724137931034483}, {"source": 5, "target": 12, "weight": 0.13333333333333333}, {"source": 6, "target": 7, "weight": 0.1111111111111111}, {"source": 6, "target": 8, "weight": 0.35555555555555557}, {"source": 6, "target": 9, "weight": 0.08888888888888889}, {"source": 7, "target": 10, "weight": 0.3333333333333333}, {"source": 7, "target": 12, "weight": 0.3333333333333333}, {"source": 8, "target": 11, "weight": 0.13333333333333333}, {"source": 8, "target": 10, "weight": 0.1111111111111111}, {"source": 8, "target": 12, "weight": 0.3333333333333333}, {"source": 8, "target": 13, "weight": 0.1111111111111111}, {"source": 9, "target": 11, "weight": 0.13333333333333333}, {"source": 9, "target": 12, "weight": 0.2}, {"source": 9, "target": 13, "weight": 0.26666666666666666}, {"source": 10, "target": 14, "weight": 0.3076923076923077}, {"source": 10, "target": 15, "weight": 0.3076923076923077}, {"source": 11, "target": 15, "weight": 0.1724137931034483}, {"source": 12, "target": 14, "weight": 0.16666666666666666}, {"source": 12, "target": 15, "weight": 0.2}, {"source": 13, "target": 15, "weight": 0.125}], "multigraph": false}