{"directed": false, "graph": [], "nodes": [{"name": "rh_inferiorparietal", "weight": 0.21212121212121213, "pos": [6, 95], "ts_group_id": 0, "label": "inferiorparietal", "input_id": 19, "layer_pos": 2, "y": 95, "x": 6, "brain_side": "right", "id": 155, "func_id": "7"}, {"name": "rh_rostralmiddlefrontal", "weight": 0.2727272727272727, "pos": [0, 35], "ts_group_id": 0, "label": "rostralmiddlefrontal", "input_id": 7, "layer_pos": 0, "y": 35, "x": 0, "brain_side": "right", "id": 7, "func_id": "6"}, {"name": "rh_caudalmiddlefrontal", "weight": 0.6363636363636364, "pos": [0, 45], "ts_group_id": 0, "label": "caudalmiddlefrontal", "input_id": 9, "layer_pos": 0, "y": 45, "x": 0, "brain_side": "right", "id": 9, "func_id": "6"}, {"name": "rh_rostralmiddlefrontal", "weight": 0.21212121212121213, "pos": [3, 35], "ts_group_id": 0, "label": "rostralmiddlefrontal", "input_id": 7, "layer_pos": 1, "y": 35, "x": 3, "brain_side": "right", "id": 75, "func_id": "6"}, {"name": "rh_caudalmiddlefrontal", "weight": 0.8787878787878788, "pos": [3, 45], "ts_group_id": 0, "label": "caudalmiddlefrontal", "input_id": 9, "layer_pos": 1, "y": 45, "x": 3, "brain_side": "right", "id": 77, "func_id": "6"}, {"name": "lh_caudalmiddlefrontal", "weight": 0.18181818181818182, "pos": [3, 215], "ts_group_id": 0, "label": "caudalmiddlefrontal", "input_id": 43, "layer_pos": 1, "y": 215, "x": 3, "brain_side": "left", "id": 111, "func_id": "7"}, {"name": "rh_caudalmiddlefrontal", "weight": 0.7575757575757576, "pos": [6, 45], "ts_group_id": 0, "label": "caudalmiddlefrontal", "input_id": 9, "layer_pos": 2, "y": 45, "x": 6, "brain_side": "right", "id": 145, "func_id": "6"}, {"name": "rh_inferiorparietal", "weight": 0.42424242424242425, "pos": [0, 95], "ts_group_id": 0, "label": "inferiorparietal", "input_id": 19, "layer_pos": 0, "y": 95, "x": 0, "brain_side": "right", "id": 19, "func_id": "7"}, {"name": "rh_caudalmiddlefrontal", "weight": 0.48484848484848486, "pos": [9, 45], "ts_group_id": 0, "label": "caudalmiddlefrontal", "input_id": 9, "layer_pos": 3, "y": 45, "x": 9, "brain_side": "right", "id": 213, "func_id": "6"}, {"name": "rh_inferiorparietal", "weight": 0.48484848484848486, "pos": [3, 95], "ts_group_id": 0, "label": "inferiorparietal", "input_id": 19, "layer_pos": 1, "y": 95, "x": 3, "brain_side": "right", "id": 87, "func_id": "7"}, {"name": "rh_caudalmiddlefrontal", "weight": 0.18181818181818182, "pos": [12, 45], "ts_group_id": 0, "label": "caudalmiddlefrontal", "input_id": 9, "layer_pos": 4, "y": 45, "x": 12, "brain_side": "right", "id": 281, "func_id": "6"}, {"name": "rh_rostralmiddlefrontal", "weight": 0.21212121212121213, "pos": [6, 35], "ts_group_id": 0, "label": "rostralmiddlefrontal", "input_id": 7, "layer_pos": 2, "y": 35, "x": 6, "brain_side": "right", "id": 143, "func_id": "6"}], "links": [{"source": 0, "target": 8}, {"source": 0, "target": 3}, {"source": 0, "target": 4}, {"source": 0, "target": 9}, {"source": 1, "target": 3}, {"source": 1, "target": 4}, {"source": 1, "target": 9}, {"source": 2, "target": 5}, {"source": 2, "target": 3}, {"source": 2, "target": 4}, {"source": 2, "target": 9}, {"source": 3, "target": 11}, {"source": 3, "target": 6}, {"source": 3, "target": 7}, {"source": 4, "target": 11}, {"source": 4, "target": 6}, {"source": 4, "target": 7}, {"source": 5, "target": 6}, {"source": 6, "target": 8}, {"source": 6, "target": 9}, {"source": 7, "target": 9}, {"source": 8, "target": 10}, {"source": 8, "target": 11}, {"source": 9, "target": 11}], "multigraph": false}