{"directed": false, "graph": [], "nodes": [{"slice_pos": 0, "name": "rh_superiortemporal", "weight": 0.17647058823529413, "pos": [0, 160], "ts_group_id": 0, "label": "superiortemporal", "input_id": 32, "func_id": "2", "y": 160, "x": 0, "brain_side": "right", "id": 32}, {"slice_pos": 1, "name": "rh_middletemporal", "weight": 0.19852941176470587, "pos": [3, 150], "ts_group_id": 0, "label": "middletemporal", "input_id": 30, "func_id": "7", "y": 150, "x": 3, "brain_side": "right", "id": 98}, {"slice_pos": 1, "name": "rh_bankssts", "weight": 0.41911764705882354, "pos": [3, 155], "ts_group_id": 0, "label": "bankssts", "input_id": 31, "func_id": "2", "y": 155, "x": 3, "brain_side": "right", "id": 99}, {"slice_pos": 1, "name": "rh_superiortemporal", "weight": 0.4117647058823529, "pos": [3, 160], "ts_group_id": 0, "label": "superiortemporal", "input_id": 32, "func_id": "2", "y": 160, "x": 3, "brain_side": "right", "id": 100}, {"slice_pos": 1, "name": "rh_transversetemporal", "weight": 0.3014705882352941, "pos": [3, 165], "ts_group_id": 0, "label": "transversetemporal", "input_id": 33, "func_id": "2", "y": 165, "x": 3, "brain_side": "right", "id": 101}, {"slice_pos": 1, "name": "rh_insula", "weight": 0.41911764705882354, "pos": [3, 170], "ts_group_id": 0, "label": "insula", "input_id": 34, "func_id": "4", "y": 170, "x": 3, "brain_side": "right", "id": 102}, {"slice_pos": 2, "name": "rh_bankssts", "weight": 0.3602941176470588, "pos": [6, 155], "ts_group_id": 0, "label": "bankssts", "input_id": 31, "func_id": "2", "y": 155, "x": 6, "brain_side": "right", "id": 167}, {"slice_pos": 2, "name": "rh_superiortemporal", "weight": 0.29411764705882354, "pos": [6, 160], "ts_group_id": 0, "label": "superiortemporal", "input_id": 32, "func_id": "2", "y": 160, "x": 6, "brain_side": "right", "id": 168}, {"slice_pos": 2, "name": "rh_transversetemporal", "weight": 0.27205882352941174, "pos": [6, 165], "ts_group_id": 0, "label": "transversetemporal", "input_id": 33, "func_id": "2", "y": 165, "x": 6, "brain_side": "right", "id": 169}, {"slice_pos": 2, "name": "rh_insula", "weight": 0.2867647058823529, "pos": [6, 170], "ts_group_id": 0, "label": "insula", "input_id": 34, "func_id": "4", "y": 170, "x": 6, "brain_side": "right", "id": 170}, {"slice_pos": 0, "name": "rh_insula", "weight": 0.3235294117647059, "pos": [0, 170], "ts_group_id": 0, "label": "insula", "input_id": 34, "func_id": "4", "y": 170, "x": 0, "brain_side": "right", "id": 34}, {"slice_pos": 0, "name": "rh_supramarginal", "weight": 0.18382352941176472, "pos": [0, 85], "ts_group_id": 0, "label": "supramarginal", "input_id": 17, "func_id": "4", "y": 85, "x": 0, "brain_side": "right", "id": 17}, {"slice_pos": 1, "name": "rh_supramarginal", "weight": 0.3235294117647059, "pos": [3, 85], "ts_group_id": 0, "label": "supramarginal", "input_id": 17, "func_id": "4", "y": 85, "x": 3, "brain_side": "right", "id": 85}, {"slice_pos": 2, "name": "rh_supramarginal", "weight": 0.2867647058823529, "pos": [6, 85], "ts_group_id": 0, "label": "supramarginal", "input_id": 17, "func_id": "4", "y": 85, "x": 6, "brain_side": "right", "id": 153}, {"slice_pos": 0, "name": "rh_bankssts", "weight": 0.22794117647058823, "pos": [0, 155], "ts_group_id": 0, "label": "bankssts", "input_id": 31, "func_id": "2", "y": 155, "x": 0, "brain_side": "right", "id": 31}], "links": [{"source": 0, "target": 1, "weight": 0.03614457831325301}, {"source": 0, "target": 2, "weight": 0.1686746987951807}, {"source": 0, "target": 3, "weight": 0.2891566265060241}, {"source": 0, "target": 4, "weight": 0.1566265060240964}, {"source": 0, "target": 5, "weight": 0.1686746987951807}, {"source": 0, "target": 12, "weight": 0.04819277108433735}, {"source": 1, "target": 10, "weight": 0.013333333333333334}, {"source": 1, "target": 6, "weight": 0.3}, {"source": 1, "target": 7, "weight": 0.12}, {"source": 1, "target": 9, "weight": 0.04}, {"source": 1, "target": 11, "weight": 0.02040816326530612}, {"source": 1, "target": 13, "weight": 0.06}, {"source": 1, "target": 14, "weight": 0.16901408450704225}, {"source": 2, "target": 10, "weight": 0.09333333333333334}, {"source": 2, "target": 6, "weight": 0.4329896907216495}, {"source": 2, "target": 7, "weight": 0.20618556701030927}, {"source": 2, "target": 9, "weight": 0.1134020618556701}, {"source": 2, "target": 11, "weight": 0.08163265306122448}, {"source": 2, "target": 13, "weight": 0.08247422680412371}, {"source": 2, "target": 14, "weight": 0.43661971830985913}, {"source": 3, "target": 10, "weight": 0.13333333333333333}, {"source": 3, "target": 6, "weight": 0.2066115702479339}, {"source": 3, "target": 7, "weight": 0.24793388429752067}, {"source": 3, "target": 8, "weight": 0.1652892561983471}, {"source": 3, "target": 9, "weight": 0.1487603305785124}, {"source": 3, "target": 11, "weight": 0.08163265306122448}, {"source": 3, "target": 13, "weight": 0.08264462809917356}, {"source": 3, "target": 14, "weight": 0.22535211267605634}, {"source": 4, "target": 10, "weight": 0.12666666666666668}, {"source": 4, "target": 7, "weight": 0.2602739726027397}, {"source": 4, "target": 8, "weight": 0.3972602739726027}, {"source": 4, "target": 9, "weight": 0.2054794520547945}, {"source": 4, "target": 11, "weight": 0.04081632653061224}, {"source": 4, "target": 13, "weight": 0.136986301369863}, {"source": 5, "target": 10, "weight": 0.25333333333333335}, {"source": 5, "target": 6, "weight": 0.1056338028169014}, {"source": 5, "target": 7, "weight": 0.14084507042253522}, {"source": 5, "target": 8, "weight": 0.1267605633802817}, {"source": 5, "target": 9, "weight": 0.22535211267605634}, {"source": 5, "target": 11, "weight": 0.1836734693877551}, {"source": 5, "target": 13, "weight": 0.11971830985915492}, {"source": 5, "target": 14, "weight": 0.08450704225352113}, {"source": 6, "target": 12, "weight": 0.050505050505050504}, {"source": 7, "target": 12, "weight": 0.10101010101010101}, {"source": 8, "target": 12, "weight": 0.1111111111111111}, {"source": 9, "target": 12, "weight": 0.15151515151515152}, {"source": 10, "target": 12, "weight": 0.12666666666666668}, {"source": 11, "target": 12, "weight": 0.46938775510204084}, {"source": 12, "target": 13, "weight": 0.32323232323232326}, {"source": 12, "target": 14, "weight": 0.04225352112676056}], "multigraph": false}