{"directed": false, "graph": [], "nodes": [{"name": "lh_bankssts", "weight": 0.5, "pos": [0, 325], "ts_group_id": 0, "label": "bankssts", "input_id": 65, "layer_pos": 0, "y": 325, "x": 0, "brain_side": "left", "id": 65, "func_id": "7"}, {"name": "lh_bankssts", "weight": 0.3333333333333333, "pos": [3, 325], "ts_group_id": 0, "label": "bankssts", "input_id": 65, "layer_pos": 1, "y": 325, "x": 3, "brain_side": "left", "id": 133, "func_id": "7"}, {"name": "lh_parsopercularis", "weight": 0.5, "pos": [0, 200], "ts_group_id": 0, "label": "parsopercularis", "input_id": 40, "layer_pos": 0, "y": 200, "x": 0, "brain_side": "left", "id": 40, "func_id": "4"}, {"name": "lh_parstriangularis", "weight": 0.3333333333333333, "pos": [3, 195], "ts_group_id": 0, "label": "parstriangularis", "input_id": 39, "layer_pos": 1, "y": 195, "x": 3, "brain_side": "left", "id": 107, "func_id": "7"}, {"name": "lh_parsopercularis", "weight": 0.3333333333333333, "pos": [3, 200], "ts_group_id": 0, "label": "parsopercularis", "input_id": 40, "layer_pos": 1, "y": 200, "x": 3, "brain_side": "left", "id": 108, "func_id": "4"}, {"name": "lh_parstriangularis", "weight": 0.5, "pos": [6, 195], "ts_group_id": 0, "label": "parstriangularis", "input_id": 39, "layer_pos": 2, "y": 195, "x": 6, "brain_side": "left", "id": 175, "func_id": "7"}, {"name": "lh_parsopercularis", "weight": 0.5, "pos": [6, 200], "ts_group_id": 0, "label": "parsopercularis", "input_id": 40, "layer_pos": 2, "y": 200, "x": 6, "brain_side": "left", "id": 176, "func_id": "4"}], "links": [{"source": 0, "target": 4}, {"source": 0, "target": 1}, {"source": 1, "target": 2}, {"source": 1, "target": 6}, {"source": 2, "target": 3}, {"source": 2, "target": 4}, {"source": 3, "target": 6}, {"source": 3, "target": 5}, {"source": 4, "target": 6}, {"source": 4, "target": 5}], "multigraph": false}